glanscan_sprokkel78/CHANGELOG
glanscan_sprokkel78/LICENSE
glanscan_sprokkel78/README.md
glanscan_sprokkel78/__init__.py
glanscan_sprokkel78/glanscan.desktop
glanscan_sprokkel78/glanscan.png
glanscan_sprokkel78/glanscan.py
glanscan_sprokkel78/glanscan.svg
glanscan_sprokkel78/install.sh
glanscan_sprokkel78/uninstall.sh
glanscan_sprokkel78/screenshots/glanscan.png
glanscan_sprokkel78-1.0.2.dist-info/METADATA
glanscan_sprokkel78-1.0.2.dist-info/WHEEL
glanscan_sprokkel78-1.0.2.dist-info/licenses/LICENSE
glanscan_sprokkel78-1.0.2.dist-info/RECORD
