Metadata-Version: 2.1
Name: glanscan_sprokkel78
Version: 1.0.2
Summary: A graphical user interface in PyGTK4 for use with the nmap binary for scanning your lan and performing portscans on Ubuntu and other Linux distro's.
Author-email: Sprokkel78 <sprokkel78.bart@gmail.com>
License-File: LICENSE
Classifier: License :: OSI Approved :: MIT License
Classifier: Operating System :: POSIX :: Linux
Classifier: Programming Language :: Python :: 3.10
Requires-Python: >=3.10
